tuyau/__init__.py
tuyau/tube.py
tuyau-1.2.dist-info/LICENSE
tuyau-1.2.dist-info/METADATA
tuyau-1.2.dist-info/WHEEL
tuyau-1.2.dist-info/top_level.txt
tuyau-1.2.dist-info/RECORD
