Metadata-Version: 2.1
Name: tuyau
Version: 1.2
Summary: Tuyau is a library that allows you to process values through a sequence of steps, similar to a pipe.
Author-email: Guillaume Pouyat <guillaume.pouyat@protonmail.com>
License: MIT License
Project-URL: Homepage, https://github.com/Guiforge/tuyau
Keywords: pipe,tube,tuyau
Classifier: License :: OSI Approved :: MIT License
Classifier: Programming Language :: Python
Classifier: Programming Language :: Python :: 3 :: Only
Classifier: Intended Audience :: Developers
Classifier: Operating System :: OS Independent
Requires-Python: >=3.10
License-File: LICENSE
